slackker/__init__.py
slackker/callbacks/__init__.py
slackker/callbacks/basic.py
slackker/callbacks/keras.py
slackker/callbacks/lightning.py
slackker/utils/__init__.py
slackker/utils/ccolors.py
slackker/utils/checkker.py
slackker/utils/functions.py
slackker-1.2.36.dist-info/METADATA
slackker-1.2.36.dist-info/WHEEL
slackker-1.2.36.dist-info/licenses/LICENSE
slackker-1.2.36.dist-info/RECORD
