Metadata-Version: 2.4
Name: slackker
Version: 1.2.36
Summary: Python package for monitoring your python script & Model training status in real-time on slack & telegram.
Project-URL: Homepage, https://github.com/siddheshgunjal/slackker
Project-URL: Repository, https://github.com/siddheshgunjal/slackker
Project-URL: Issues, https://github.com/siddheshgunjal/slackker/issues
Project-URL: Changelog, https://github.com/siddheshgunjal/slackker/releases
Author-email: Siddhesh Gunjal <siddhu19@live.com>
License-Expression: Apache-2.0
License-File: LICENSE
Classifier: Intended Audience :: Developers
Classifier: Intended Audience :: Information Technology
Classifier: Intended Audience :: Science/Research
Classifier: License :: OSI Approved :: Apache Software License
Classifier: Operating System :: OS Independent
Classifier: Programming Language :: Python :: 3
Requires-Python: >=3.8
Requires-Dist: matplotlib>=3.7.5
Requires-Dist: numpy>=1.24.4
Requires-Dist: slack-sdk>=3.39.0
